[
    {
      "id": 1,
      "name": "經典輔大味",
      "price": "$50",
      "image": "images/gallery-1.jpg",
      "description": "Give your summer wardrobe a style upgrade with the HRX Men's Active T-shirt. Team it with a pair of shorts for your morning workout or a denims for an evening out with the guys.",
      
    },
    {
      "id": 2,
      "name": "日式昆布湯底",
      "price": "$75",
      "image": "images/product-9.jpg",
      "description": "Stylish and functional sport watch.",
      
    },
    {
      "id": 3,
      "name": "新鮮牛番茄湯底",
      "price": "$55",
      "image": "images/product-9.jpg",
      "description": "Stylish and functional sport watch.",
      
    },
    {
      "id": 4,
      "name": "養生佛跳牆湯底",
      "price": "$75",
      "image": "images/product-10.jpg",
      "description": "Comfortable and trendy black shoes for any occasion.",
      
    },
    {
      "id": 5,
      "name": "獨家輔大撈秘密湯底",
      "price": "$80",
      "image": "images/product-10.jpg",
      "description": "Comfortable and trendy black shoes for any occasion.",
    
    }
  ]
  